persian_wordcloud
