Metadata-Version: 1.0
Name: persian-wordcloud
Version: 1.3.0
Summary: Persian Word Cloud Generator
Home-page: https://github.com/Mehotkhan/persian-word-cloud
Author: Ali Zemani , Javad Bahoosh
Author-email: mehot1@gmail.coom , j.bahoosh@mail.sbu.ac.ir
License: MIT
Keywords: persian  wordcloud
Platform: UNKNOWN
